pypsse/__init__.py
pypsse/channel_map.py
pypsse/common.py
pypsse/compile.bat
pypsse/conec.flx
pypsse/conet.flx
pypsse/contingencies.py
pypsse/custom_logger.py
pypsse/enumerations.py
pypsse/exceptions.py
pypsse/helics_interface.py
pypsse/mdao_interface.py
pypsse/models.py
pypsse/project.py
pypsse/result_container.py
pypsse/simulation_controller.py
pypsse/simulator.py
pypsse/api/PSSE.v2.json
pypsse/api/__init__.py
pypsse/api/common.py
pypsse/api/config.yaml
pypsse/api/server.py
pypsse/api/app/__init__.py
pypsse/api/app/psse.py
pypsse/api/web/__init__.py
pypsse/api/web/handler.py
pypsse/cli/__init__.py
pypsse/cli/create_profiles.py
pypsse/cli/create_project.py
pypsse/cli/explore.py
pypsse/cli/profiles.py
pypsse/cli/pypsse.py
pypsse/cli/run.py
pypsse/cli/serve.py
pypsse/components/branch.py
pypsse/components/bus.py
pypsse/components/fixed_shunt.py
pypsse/components/generator.py
pypsse/components/load.py
pypsse/components/machine.py
pypsse/components/switched_shunt.py
pypsse/components/system.py
pypsse/components/transformer.py
pypsse/data_writers/__init__.py
pypsse/data_writers/csv.py
pypsse/data_writers/data_writer.py
pypsse/data_writers/hdf5.py
pypsse/data_writers/json.py
pypsse/defaults/__init__.py
pypsse/defaults/export_settings.toml
pypsse/defaults/simulation_settings.toml
pypsse/modes/__init__.py
pypsse/modes/abstract_mode.py
pypsse/modes/constants.py
pypsse/modes/dynamic.py
pypsse/modes/pcm.py
pypsse/modes/snap.py
pypsse/modes/static.py
pypsse/parsers/__init__.py
pypsse/parsers/gic_parser.py
pypsse/parsers/reader.py
pypsse/profile_manager/__init__.py
pypsse/profile_manager/common.py
pypsse/profile_manager/profile.py
pypsse/profile_manager/profile_store.py
pypsse/utils/__init__.py
pypsse/utils/dynamic_utils.py
pypsse/utils/utils.py
pypsse/utils/dc2ac/__init__.py
pypsse/utils/dc2ac/dc_ac_algorithm.py
pypsse/utils/dc2ac/helper_functions.py
nrel_pypsse-1.1.5.dist-info/METADATA
nrel_pypsse-1.1.5.dist-info/WHEEL
nrel_pypsse-1.1.5.dist-info/entry_points.txt
nrel_pypsse-1.1.5.dist-info/licenses/LICENSE
nrel_pypsse-1.1.5.dist-info/RECORD
